[
  {
    "UserName": "test-62c392",
    "PasswordHash": "placeholder",
    "FirstName": "Test",
    "LastName": "Korisnik",
    "Email": "test@test.rs",
    "DateOfBirth": "15/01/1995",
    "Gender": "Muski",
    "Role": "Gost",
    "Id": "30ab24a1-af5b-4c2f-af12-23c0feba0f06",
    "CreatedAt": "2026-06-09T15:33:58.7525454Z",
    "IsDeleted": false
  },
  {
    "UserName": "test-33a79c",
    "PasswordHash": "placeholder",
    "FirstName": "Test",
    "LastName": "Korisnik",
    "Email": "test@test.rs",
    "DateOfBirth": "15/01/1995",
    "Gender": "Muski",
    "Role": "Gost",
    "Id": "b5e752c5-0bf0-4410-aa62-c4eeab478f82",
    "CreatedAt": "2026-06-09T15:35:00.432291Z",
    "IsDeleted": false
  },
  {
    "UserName": "test-d52ad4",
    "PasswordHash": "placeholder",
    "FirstName": "Test",
    "LastName": "Korisnik",
    "Email": "test@test.rs",
    "DateOfBirth": "15/01/1995",
    "Gender": "Muski",
    "Role": "Gost",
    "Id": "d365c258-2425-4343-936a-621d9f5ca5e5",
    "CreatedAt": "2026-06-11T20:00:31.2992721Z",
    "IsDeleted": false
  },
  {
    "UserName": "test-a7fa9f",
    "PasswordHash": "placeholder",
    "FirstName": "Test",
    "LastName": "Korisnik",
    "Email": "test@test.rs",
    "DateOfBirth": "15/01/1995",
    "Gender": "Muski",
    "Role": "Gost",
    "Id": "487429c0-4a8f-4ba1-bd40-335ba60d87fd",
    "CreatedAt": "2026-06-11T20:01:34.0028101Z",
    "IsDeleted": false
  },
  {
    "UserName": "test-c0d203",
    "PasswordHash": "placeholder",
    "FirstName": "Test",
    "LastName": "Korisnik",
    "Email": "test@test.rs",
    "DateOfBirth": "15/01/1995",
    "Gender": "Muski",
    "Role": "Gost",
    "Id": "26737118-0043-4036-a58e-944f4a94d447",
    "CreatedAt": "2026-06-11T20:05:12.816433Z",
    "IsDeleted": false
  },
  {
    "UserName": "test-31d8cf",
    "PasswordHash": "placeholder",
    "FirstName": "Test",
    "LastName": "Korisnik",
    "Email": "test@test.rs",
    "DateOfBirth": "15/01/1995",
    "Gender": "Muski",
    "Role": "Gost",
    "Id": "9fc7cacb-06e8-4598-ae9c-05053038e0d1",
    "CreatedAt": "2026-06-11T20:07:52.8742316Z",
    "IsDeleted": false
  },
  {
    "UserName": "test-cf6b8b",
    "PasswordHash": "placeholder",
    "FirstName": "Test",
    "LastName": "Korisnik",
    "Email": "test@test.rs",
    "DateOfBirth": "15/01/1995",
    "Gender": "Muski",
    "Role": "Gost",
    "Id": "ba76f104-6472-467d-b372-060cf7ef61cb",
    "CreatedAt": "2026-06-11T20:34:57.0489778Z",
    "IsDeleted": false
  },
  {
    "UserName": "test-0cc4c6",
    "PasswordHash": "placeholder",
    "FirstName": "Test",
    "LastName": "Korisnik",
    "Email": "test@test.rs",
    "DateOfBirth": "15/01/1995",
    "Gender": "Muski",
    "Role": "Gost",
    "Id": "54df0244-1875-43ea-9d69-6607bb040ed5",
    "CreatedAt": "2026-06-11T20:40:39.0224411Z",
    "IsDeleted": false
  },
  {
    "UserName": "test-106635",
    "PasswordHash": "placeholder",
    "FirstName": "Test",
    "LastName": "Korisnik",
    "Email": "test@test.rs",
    "DateOfBirth": "15/01/1995",
    "Gender": "Muski",
    "Role": "Gost",
    "Id": "94b146bb-edcb-4dc9-9ac8-da508e3c59aa",
    "CreatedAt": "2026-06-11T20:45:25.5049885Z",
    "IsDeleted": false
  },
  {
    "UserName": "test-416e7d",
    "PasswordHash": "placeholder",
    "FirstName": "Test",
    "LastName": "Korisnik",
    "Email": "test@test.rs",
    "DateOfBirth": "15/01/1995",
    "Gender": "Muski",
    "Role": "Gost",
    "Id": "536d5d6a-e805-4861-9041-9e56f5840d69",
    "CreatedAt": "2026-06-11T20:54:58.6496756Z",
    "IsDeleted": false
  },
  {
    "UserName": "test-77f6dd",
    "PasswordHash": "placeholder",
    "FirstName": "Test",
    "LastName": "Korisnik",
    "Email": "test@test.rs",
    "DateOfBirth": "15/01/1995",
    "Gender": "Muski",
    "Role": "Gost",
    "Id": "d905a5fa-c266-4488-90ce-c0d6526adfca",
    "CreatedAt": "2026-06-11T20:57:49.2648713Z",
    "IsDeleted": false
  },
  {
    "UserName": "test-2ec65b",
    "PasswordHash": "placeholder",
    "FirstName": "Test",
    "LastName": "Korisnik",
    "Email": "test@test.rs",
    "DateOfBirth": "15/01/1995",
    "Gender": "Muski",
    "Role": "Gost",
    "Id": "4df56274-336d-4639-ba5e-98ff69c86bbe",
    "CreatedAt": "2026-06-11T21:03:46.6151335Z",
    "IsDeleted": false
  },
  {
    "UserName": "test-94977e",
    "PasswordHash": "placeholder",
    "FirstName": "Test",
    "LastName": "Korisnik",
    "Email": "test@test.rs",
    "DateOfBirth": "15/01/1995",
    "Gender": "Muski",
    "Role": "Gost",
    "Id": "a76dec1c-0f02-45ac-bf80-ae9192467644",
    "CreatedAt": "2026-06-11T21:28:33.5649438Z",
    "IsDeleted": false
  },
  {
    "UserName": "test-a1743c",
    "PasswordHash": "placeholder",
    "FirstName": "Test",
    "LastName": "Korisnik",
    "Email": "test@test.rs",
    "DateOfBirth": "15/01/1995",
    "Gender": "Muski",
    "Role": "Gost",
    "Id": "be64038e-64d9-4071-9cb2-f2b277ff59ff",
    "CreatedAt": "2026-06-12T06:11:14.267621Z",
    "IsDeleted": false
  },
  {
    "UserName": "test-95abba",
    "PasswordHash": "placeholder",
    "FirstName": "Test",
    "LastName": "Korisnik",
    "Email": "test@test.rs",
    "DateOfBirth": "15/01/1995",
    "Gender": "Muski",
    "Role": "Gost",
    "Id": "cb09f9d5-be28-4727-b676-bfe4a9c28e4e",
    "CreatedAt": "2026-06-12T06:11:40.1960341Z",
    "IsDeleted": false
  },
  {
    "UserName": "test-e06ddf",
    "PasswordHash": "placeholder",
    "FirstName": "Test",
    "LastName": "Korisnik",
    "Email": "test@test.rs",
    "DateOfBirth": "15/01/1995",
    "Gender": "Muski",
    "Role": "Gost",
    "Id": "f532db21-232e-4f73-98a8-42518ab4ca8d",
    "CreatedAt": "2026-06-12T06:27:40.2568399Z",
    "IsDeleted": false
  },
  {
    "UserName": "marko",
    "PasswordHash": "100000.gYxx4lkRoH6lX5fuErqbrA==.xKqquBT0JJMk7neWPrRrUXWCYHEJWpIiWLn8nLVoIy0=",
    "FirstName": "Marko",
    "LastName": "Petrović",
    "Email": "marko@test.rs",
    "DateOfBirth": "12/03/1985",
    "Gender": "Muski",
    "Role": "Domacin",
    "Id": "5ee9e4be-b730-4f42-ab68-8bbafd9ceea1",
    "CreatedAt": "2026-06-12T07:08:05.7753111Z",
    "IsDeleted": false
  },
  {
    "UserName": "ana",
    "PasswordHash": "100000.1T7cQWDbBRLNudRUOhPHPA==.SOpWxj1tcblyKsSK8oRbioFu7740VXUr9v4sneEv25I=",
    "FirstName": "Ana",
    "LastName": "Jovanović",
    "Email": "ana@test.rs",
    "DateOfBirth": "07/09/1990",
    "Gender": "Zenski",
    "Role": "Domacin",
    "Id": "3ada06fd-c901-4835-9fab-936e49ad3a3f",
    "CreatedAt": "2026-06-12T07:08:06.564399Z",
    "IsDeleted": false
  },
  {
    "UserName": "stefan",
    "PasswordHash": "100000.bdSzs+AD9C1huokbiQL1HQ==.UKW72gAiaTXdgOVLSg8zgM03DXSpiwSP4tCbKwdthQI=",
    "FirstName": "Stefan",
    "LastName": "Nikolić",
    "Email": "stefan@test.rs",
    "DateOfBirth": "23/11/1982",
    "Gender": "Muski",
    "Role": "Domacin",
    "Id": "cd350c2d-ffa6-497f-a4e0-0882147dc7fd",
    "CreatedAt": "2026-06-12T07:08:07.3282917Z",
    "IsDeleted": false
  },
  {
    "UserName": "jovana",
    "PasswordHash": "100000.q8ZW2nzujNib5VU+/RszJQ==.AcOlgsMCdT6GkKla4KXNyr3oQ2N9hVdyJcyPpMJtWno=",
    "FirstName": "Jovana",
    "LastName": "Mitrović",
    "Email": "jovana@test.rs",
    "DateOfBirth": "04/06/1992",
    "Gender": "Zenski",
    "Role": "Domacin",
    "Id": "99c13017-fd51-4b98-9c94-6a6cc0144588",
    "CreatedAt": "2026-06-12T07:08:08.100274Z",
    "IsDeleted": false
  },
  {
    "UserName": "petar",
    "PasswordHash": "100000.HBoPlpU+wCm+4yciupA2WQ==.5QWDOD4aJjKdRHjYV/X3kTgovu1Yui7zRlzFz1c2RtE=",
    "FirstName": "Petar",
    "LastName": "Đorđević",
    "Email": "petar@test.rs",
    "DateOfBirth": "18/02/1995",
    "Gender": "Muski",
    "Role": "Gost",
    "Id": "31810fb6-894b-4ae4-8cc9-7d60359ef312",
    "CreatedAt": "2026-06-12T07:08:08.7857336Z",
    "IsDeleted": false
  },
  {
    "UserName": "milica",
    "PasswordHash": "100000.ctXU0V7fgISoiZUXG0xsAg==.dY+cSc4a+CcDcxwKcIrtqfCboqpBse3kqe1fsYNALHE=",
    "FirstName": "Milica",
    "LastName": "Stojanović",
    "Email": "milica@test.rs",
    "DateOfBirth": "29/08/1998",
    "Gender": "Zenski",
    "Role": "Gost",
    "Id": "dee83ef1-ced6-4b35-aeea-5b136c0d6c6b",
    "CreatedAt": "2026-06-12T07:08:09.4555091Z",
    "IsDeleted": false
  },
  {
    "UserName": "nikola",
    "PasswordHash": "100000.ytgxSxHOKCBBnx4hV8r42Q==.EGzbq1s8RVa6XAJ51tVQALJ1GOQ4sAB8TBM2gwvNTQc=",
    "FirstName": "Nikola",
    "LastName": "Lazarević",
    "Email": "nikola@test.rs",
    "DateOfBirth": "11/12/1993",
    "Gender": "Muski",
    "Role": "Gost",
    "Id": "c82e2292-2957-4524-b803-5240ecb62214",
    "CreatedAt": "2026-06-12T07:08:10.144974Z",
    "IsDeleted": false
  },
  {
    "UserName": "Moew",
    "PasswordHash": "100000.I+VtoTuDagCgRn7SOIgaig==.CagVze9jbe4xFBja4o9YBKNe54M0aPrVHMsLCrp83Ew=",
    "FirstName": "Ignjat",
    "LastName": "Radojicic",
    "Email": "ignjatradojicic@gmail.com",
    "DateOfBirth": "11/06/2004",
    "Gender": "Muski",
    "Role": "Gost",
    "Id": "2820bd7d-d923-4fda-bb14-f5b91dfb93c9",
    "CreatedAt": "2026-06-12T13:00:51.2896401Z",
    "IsDeleted": false
  },
  {
    "UserName": "srpskifornite@gmail.com",
    "PasswordHash": "100000.Fur2zCqxcbM4iCoR8flx7Q==.UNoTTl5k+cm9DWrfqo8MclnEBJ37Joy0HYKrt4qF6bA=",
    "FirstName": "Ignjat",
    "LastName": "Radojicic",
    "Email": "srpskifornite@gmail.com",
    "DateOfBirth": "04/06/2026",
    "Gender": "Muski",
    "Role": "Gost",
    "Id": "9b8e997a-9583-4a5b-927b-428b1f126616",
    "CreatedAt": "2026-06-12T13:16:32.2099628Z",
    "IsDeleted": false
  },
  {
    "UserName": "Ignjat",
    "PasswordHash": "100000.8ckIlgiPQpAfS+n2zBzaAA==.EcOzsU9URIDLjo4daLE2AB2k22NTkY5kurimJk+l9zI=",
    "FirstName": "Ignjat",
    "LastName": "Ignjat",
    "Email": "ignjatrad1ojicic@gmail.com",
    "DateOfBirth": "02/03/2026",
    "Gender": "Muski",
    "Role": "Gost",
    "Id": "cd489431-00c8-434e-a036-377941f48c67",
    "CreatedAt": "2026-06-12T13:24:53.7962536Z",
    "IsDeleted": false
  },
  {
    "UserName": "Ignjat2",
    "PasswordHash": "100000.xeCTxJzrT25Jum8hhFWQxA==.wqAnc2yNdGZBL0oK7KpreDesHahGA4zh8WhsXOIxwUQ=",
    "FirstName": "Ignjat2",
    "LastName": "Ignjat2",
    "Email": "Ignjat2@gmail.com",
    "DateOfBirth": "22/02/2004",
    "Gender": "Muski",
    "Role": "Gost",
    "Id": "424c8612-1ec9-4a09-a8fb-d3280c2a78ea",
    "CreatedAt": "2026-06-12T21:03:32.8919768Z",
    "IsDeleted": false
  },
  {
    "UserName": "admin",
    "PasswordHash": "100000.rRMmNJ8Naq9vht8vImbIeQ==.kxVLyFhF0Yy77gtBQuJrYzrgQv9tuapJVFahQ54VfrI=",
    "FirstName": "Admin",
    "LastName": "RezervisiMe",
    "Email": "admin@rezervisi.me",
    "DateOfBirth": "01/01/1990",
    "Gender": "Muski",
    "Role": "Administrator",
    "Id": "ebd55eac-fb82-42c9-bfd1-c3e9e75fa424",
    "CreatedAt": "2026-06-12T21:20:01.8760839Z",
    "IsDeleted": false
  }
]